pipeline_logger/__init__.py
pipeline_logger/kafka_handler.py
pipeline_logger/tensorboard_handler.py
pipeline_logger-1.0.2.dist-info/DESCRIPTION.rst
pipeline_logger-1.0.2.dist-info/METADATA
pipeline_logger-1.0.2.dist-info/RECORD
pipeline_logger-1.0.2.dist-info/WHEEL
pipeline_logger-1.0.2.dist-info/metadata.json
pipeline_logger-1.0.2.dist-info/top_level.txt
