Metadata-Version: 2.0
Name: pipeline-logger
Version: 1.0.2
Summary: PipelineAI Logger
Home-page: https://github.com/PipelineAI/pip/
Author: Chris Fregly
Author-email: github@pipeline.ai
License: UNKNOWN
Platform: UNKNOWN
Requires-Dist: kafka-python (==1.3.4)
Requires-Dist: tensorboard-logger (==0.0.4)
